setup.py
django_navware.egg-info/PKG-INFO
django_navware.egg-info/SOURCES.txt
django_navware.egg-info/dependency_links.txt
django_navware.egg-info/top_level.txt
navware/__init__.py
navware/apps.py
navware/defaults.py
navware/nav.py
navware/tests/__init__.py
navware/tests/tests_nav.py
navware/tests/testsettings.py