Metadata-Version: 1.1
Name: django-navware
Version: 0.0.1
Summary: A simple yet effective navigation system for Django apps.
Home-page: https://github.com/un33k/django-navware
Author: Val Neekman
Author-email: info@neekware.com
License: BSD
Platform: UNKNOWN
Classifier: Development Status :: 3 - Alpha
Classifier: Environment :: Web Environment
Classifier: Intended Audience :: Developers
Classifier: License :: OSI Approved :: BSD License
Classifier: Operating System :: OS Independent
Classifier: Programming Language :: Python
Classifier: Topic :: Utilities
